{
  "id": "D05",
  "assetId": "Weapon_Full_D05",
  "name": "Incalculable Factor",
  "rarity": "SSR",
  "realm": "ULTRA",
  "awakener": "winkle",
  "ownerAwakenerId": 53,
  "ownerAwakenerName": "winkle",
  "aliases": ["Incalculable Factor"],
  "searchTags": [],
  "mainstatKey": "ALIEMUS_REGEN",
  "mainstatSeriesKey": "SSR:ALIEMUS_REGEN",
  "descriptionTemplate": "Team Unique: The Aliemus generated by the wielder increases by [StateArg1]%. The wielder gains [StateArg2]  Keyflare after releasing Exalt.",
  "descriptionArgs": {
    "StateArg1": {"kind": "scaling", "values": ["9", "11", "13", "15"]},
    "StateArg2": {"kind": "scaling", "values": ["140", "160", "180", "200"]}
  }
}
