{
  "schemaVersion": 3,
  "kind": "derivedSkill",
  "id": "derived.daffodil.thousand-mirage-effect-critical-hit",
  "name": "Critical Hit",
  "route": {
    "slug": "critical-hit",
    "canonicalPath": "/database/awakeners/daffodil/derived-skills/critical-hit"
  },
  "ownerAwakenerId": "awakener-0012",
  "derivedFromId": "derived.daffodil.thousand-mirage-extra-effects",
  "rootSkillId": "skill.daffodil.sea-of-primordial-essence",
  "descriptionTemplate": "Increase Crit. Rate by [Arg1]% and Crit. DMG by [Arg2]%.",
  "descriptionArgs": {
    "Arg1": {
      "kind": "fixed",
      "value": "50",
      "suffix": "%"
    },
    "Arg2": {
      "kind": "fixed",
      "value": "25",
      "suffix": "%"
    }
  },
  "cardKeywords": [],
  "cost": "0",
  "ownerAwakenerName": "Daffodil"
}
