{
  "schemaVersion": 3,
  "kind": "derivedSkill",
  "id": "derived.global.fleeting-beauty",
  "name": "Fleeting Beauty",
  "route": {
    "slug": "fleeting-beauty",
    "canonicalPath": "/database/derived-skills/fleeting-beauty"
  },
  "descriptionTemplate": "Place 1 \"Strike\" with Arithmetica Cost 0 into hand for each Awakener, and attach {Exhaust}. Replace all Awakener cards in your hand with \"Strike\" with Arithmetica Cost 0 until the turn ends.",
  "descriptionArgs": {},
  "cardKeywords": [
    {
      "id": "mechanic.exhaust"
    },
    {
      "id": "mechanic.retain"
    }
  ],
  "cost": "0"
}
