[
  {
    "id": "016",
    "pieces": ["xp", "6", "g", "N", "K", "xC"]
  },
  {
    "id": "013",
    "pieces": ["J", "xS", "xU", "xo", "v", "yd"]
  },
  {
    "id": "010",
    "pieces": ["Y", "x8", "xL", "t", "yf", "3"]
  },
  {
    "id": "011",
    "pieces": ["9", "2", "xd", "xV", "yc", "xc"]
  },
  {
    "id": "017",
    "pieces": ["G", "e", "xv", "xE", "xs", "C"]
  },
  {
    "id": "005",
    "pieces": ["yv", "yC", "O", "n", "yu", "D"]
  },
  {
    "id": "001",
    "pieces": ["xB", "yn", "yh", "xF", "xM", "yA"]
  },
  {
    "id": "012",
    "pieces": ["xQ", "A", "j", "V", "xn", "xe"]
  },
  {
    "id": "002",
    "pieces": ["xl", "S", "x5", "xZ", "xT", "7"]
  },
  {
    "id": "015",
    "pieces": ["yt", "k", "ys", "yD", "H", "xm"]
  },
  {
    "id": "019",
    "pieces": ["Z", "xO", "i", "xK", "r", "xg"]
  },
  {
    "id": "018",
    "pieces": ["4", "ye", "xi", "B", "yg", "x0"]
  },
  {
    "id": "014",
    "pieces": ["yB", "yj", "5", "q", "xr", "yl"]
  },
  {
    "id": "009",
    "pieces": ["s", "8", "L", "xY", "U", "c"]
  },
  {
    "id": "004",
    "pieces": ["x9", "yk", "F", "R", "xt", "f"]
  },
  {
    "id": "021",
    "pieces": ["d", "p", "w", "P", "x2", "yq"]
  },
  {
    "id": "022",
    "pieces": ["xf", "h", "Q", "u", "E", "xR"]
  },
  {
    "id": "020",
    "pieces": ["ym", "xh", "yE", "x6", "T", "xD"]
  },
  {
    "id": "006",
    "pieces": ["x4", "yi", "xN", "xG", "M", "xj"]
  },
  {
    "id": "023",
    "pieces": ["yw", "X", "yp", "yo", "xu", "x7"]
  },
  {
    "id": "008",
    "pieces": ["xA", "xX", "I", "W", "xw", "xb"]
  }
]
