{
  "id": 46,
  "key": "sorel",
  "displayName": "sorel",
  "ingameId": "B04",
  "faction": "Outlanders",
  "realm": "CARO",
  "rarity": "SSR",
  "type": "ASSAULT",
  "aliases": ["sorel"],
  "searchTags": ["Death Resistance", "Heal", "Self-Harm"],
  "stats": {
    "CON": "131",
    "ATK": "185",
    "DEF": "95",
    "CritRate": "14.6%",
    "CritDamage": "57.2%",
    "AliemusRegen": "0",
    "KeyflareRegen": "15",
    "RealmMastery": "0",
    "SigilYield": "0%",
    "DamageAmplification": "0%",
    "DeathResistance": "0%"
  },
  "primaryScalingBase": 30,
  "statScaling": {
    "CON": 1.45,
    "ATK": 2.05,
    "DEF": 1.05
  },
  "substatScaling": {
    "CritRate": "1.6%",
    "CritDamage": "1.2%"
  },
  "assets": {
    "portraitKey": "sorel",
    "iconKey": "sorel"
  },
  "cards": {
    "C1": {
      "descriptionTemplate": "Sorel obtains [Energy:Arg1] Aliemus. {Rouse}: Obtain [Power:Arg2] {STR}. For each instance of DMG dealt by Sorel, obtain [Power:Arg3] Temporary {STR}.",
      "descriptionArgs": {
        "Arg1": {
          "kind": "scaling",
          "values": ["25", "30", "35", "40", "45", "50"]
        },
        "Arg2": {
          "kind": "scaling",
          "values": ["4.5", "5.4", "6.3", "7.2", "8.1", "9"],
          "suffix": "%",
          "stat": "ATK"
        },
        "Arg3": {
          "kind": "scaling",
          "values": ["1.5", "1.8", "2.1", "2.4", "2.7", "3"],
          "suffix": "%",
          "stat": "ATK"
        }
      },
      "id": "skill.sorel.host-ladys-privilege",
      "ownerAwakenerId": 46,
      "kind": "rouse",
      "displayName": "Host Lady's Privilege",
      "cost": "2",
      "cardKeywords": [
        {
          "id": "mechanic.retain"
        }
      ],
      "variants": []
    },
    "C2": {
      "descriptionTemplate": "Deal [Damage:Arg1] DMG. Sorel obtains [Energy:Arg2] Aliemus.",
      "descriptionArgs": {
        "Arg1": {
          "kind": "scaling",
          "values": ["10", "12", "14", "16", "18", "20"],
          "suffix": "%",
          "stat": "ATK"
        },
        "Arg2": {
          "kind": "scaling",
          "values": ["5", "6", "7", "8", "9", "10"]
        }
      },
      "id": "skill.sorel.strike",
      "ownerAwakenerId": 46,
      "kind": "strike",
      "displayName": "Strike",
      "cost": "1",
      "cardKeywords": [],
      "variants": []
    },
    "C3": {
      "descriptionTemplate": "Obtain [Block:Arg1] Shield. Sorel obtains [Energy:Arg3] Aliemus.",
      "descriptionArgs": {
        "Arg1": {
          "kind": "scaling",
          "values": ["10", "12", "14", "16", "18", "20"],
          "suffix": "%",
          "stat": "DEF"
        },
        "Arg3": {
          "kind": "scaling",
          "values": ["5", "6", "7", "8", "9", "10"]
        }
      },
      "id": "skill.sorel.defense",
      "ownerAwakenerId": 46,
      "kind": "defense",
      "displayName": "Defense",
      "cost": "1",
      "cardKeywords": [],
      "variants": []
    },
    "C4": {
      "descriptionTemplate": "Randomly deal [Damage:Arg1] DMG [Arg3] times. Restore [Heal:Arg2] HP at turn end.",
      "descriptionArgs": {
        "Arg1": {
          "kind": "scaling",
          "values": ["12", "14.4", "16.8", "19.2", "21.6", "24"],
          "suffix": "%",
          "stat": "ATK"
        },
        "Arg3": {
          "kind": "fixed",
          "value": "4"
        },
        "Arg2": {
          "kind": "scaling",
          "values": ["10", "12", "14", "16", "18", "20"],
          "suffix": "%",
          "stat": "CON"
        }
      },
      "id": "skill.sorel.elegance-of-rose",
      "ownerAwakenerId": 46,
      "kind": "command",
      "displayName": "Elegance of Rose",
      "cost": "2",
      "cardKeywords": [],
      "variants": []
    },
    "C5": {
      "descriptionTemplate": "Lose [Arg1]% Current HP.{Embryo Fusion} +[Blood:Arg2]%. During this turn, recover [Arg3] HP at turn end for each instance of DMG dealt.",
      "descriptionArgs": {
        "Arg1": {
          "kind": "fixed",
          "value": "10"
        },
        "Arg2": {
          "kind": "scaling",
          "values": ["30", "32", "34", "36", "38", "40"]
        },
        "Arg3": {
          "kind": "scaling",
          "values": ["1.5", "1.8", "2.1", "2.4", "2.7", "3"],
          "suffix": "%",
          "stat": "CON"
        }
      },
      "id": "skill.sorel.diamond-in-the-rough",
      "ownerAwakenerId": 46,
      "kind": "command",
      "displayName": "Diamond in the Rough",
      "cost": "1",
      "cardKeywords": [],
      "variants": []
    },
    "Exalt": {
      "descriptionTemplate": "[{Infinite Devour}: This {Carousel of Ambition} deals +[Arg3] instances of DMG, HP Recovery +[Heal:Arg6].] Randomly deal [Damage:Arg2] DMG [Arg1] times. Restore [Heal:Arg4] HP at turn end.",
      "descriptionArgs": {
        "Arg3": {
          "kind": "fixed",
          "value": "3"
        },
        "Arg6": {
          "kind": "scaling",
          "values": ["4", "4.8", "5.6", "6.4", "7.2", "8"],
          "suffix": "%",
          "stat": "CON"
        },
        "Arg2": {
          "kind": "scaling",
          "values": ["15", "18", "21", "24", "27", "30"],
          "suffix": "%",
          "stat": "ATK"
        },
        "Arg1": {
          "kind": "fixed",
          "value": "6"
        },
        "Arg4": {
          "kind": "scaling",
          "values": ["15", "18", "21", "24", "27", "30"],
          "suffix": "%",
          "stat": "CON"
        }
      },
      "id": "skill.sorel.carousel-of-ambition",
      "ownerAwakenerId": 46,
      "kind": "exalt",
      "displayName": "Carousel of Ambition",
      "cost": "100",
      "cardKeywords": [],
      "variants": []
    },
    "OverExalt": {
      "descriptionTemplate": "Makes the next 3 Command Cards of Sorel take effect 2 times. Each time this Exalt deals DMG, at turn end, it heals HP equal to CON [Arg1]%.",
      "descriptionArgs": {
        "Arg1": {
          "kind": "fixed",
          "value": "2.5"
        }
      },
      "id": "skill.sorel.roses-infinite-desire",
      "ownerAwakenerId": 46,
      "kind": "over_exalt",
      "displayName": "Rose's Infinite Desire",
      "cardKeywords": [],
      "variants": []
    },
    "promotedExtras": []
  },
  "talents": {
    "T1": {
      "descriptionTemplate": "For every 1% Crit. Rate Sorel and her equipped WoD & Covenant have, increase the Aliemus obtained from {Defense} by 0.2.",
      "descriptionArgs": {},
      "id": "talent.sorel.guardian-of-vanity",
      "ownerAwakenerId": 46,
      "displayName": "Guardian of Vanity",
      "upgradeTargetIds": [],
      "upgradePatches": []
    },
    "T2": {
      "descriptionTemplate": "Obtain [Arg1] Aliemus after the start of exploration.",
      "descriptionArgs": {
        "Arg1": {
          "kind": "linear",
          "base": "5",
          "gainPerLevel": "5"
        }
      },
      "id": "talent.sorel.madness-omen",
      "ownerAwakenerId": 46,
      "displayName": "Madness Omen",
      "maxLevel": 12,
      "upgradeTargetIds": [],
      "upgradePatches": []
    },
    "T3": {
      "descriptionTemplate": "This talent is only effective in the {Astral Reign} stages.\nThis Awakener's CON, ATK, and DEF are increase by [Arg1] %, and they gain [Arg2] Keyflare upon their first {Rouse}.\nSorel gains Temporary {STR} equal to [Arg3]% of her ATK after {Devour}, triggering a maximum of 5 times per round.",
      "descriptionArgs": {
        "Arg1": {
          "kind": "linear",
          "base": "3",
          "gainPerLevel": "3"
        },
        "Arg2": {
          "kind": "linear",
          "base": "50",
          "gainPerLevel": "50"
        },
        "Arg3": {
          "kind": "scaling",
          "values": ["15", "16.5", "18", "19.5", "21", "22.5", "24", "25.5", "27", "30"]
        }
      },
      "id": "talent.sorel.soulforge-aptitude",
      "ownerAwakenerId": 46,
      "displayName": "Soulforge Aptitude",
      "maxLevel": 10,
      "upgradeTargetIds": [],
      "upgradePatches": []
    },
    "extraTalents": []
  },
  "enlightens": {
    "E1": {
      "descriptionTemplate": "If current HP is below 50%, {Strike} deals 2 instances of DMG, {Embryo Fusion} +10%. {Defense} gains 2 Shield, {Embryo Fusion} +10%.",
      "descriptionArgs": {},
      "id": "enlighten.sorel.flowing-rill",
      "ownerAwakenerId": 46,
      "slot": "E1",
      "displayName": "Flowing Rill",
      "upgradeTargetIds": ["skill.sorel.defense", "skill.sorel.strike"],
      "upgradePatches": [
        {
          "targetId": "skill.sorel.strike",
          "targetType": "skill",
          "operation": "replace_description",
          "descriptionTemplate": "Deal [Damage:Arg1] DMG. If current HP is below 50%, deal an additional 1 instance of DMG, {Embryo Fusion} +[Blood:Arg3]%. Sorel obtains [Energy:Arg2] Aliemus.",
          "descriptionArgs": {
            "Arg3": {
              "kind": "fixed",
              "value": "10"
            }
          }
        },
        {
          "targetId": "skill.sorel.defense",
          "targetType": "skill",
          "operation": "replace_description",
          "descriptionTemplate": "Obtain [Block:Arg1] Shield. If current HP is below 50%, obtain an additional Shield, {Embryo Fusion} +[Blood:Arg4]%. Sorel obtains [Energy:Arg3] Aliemus.",
          "descriptionArgs": {
            "Arg4": {
              "kind": "fixed",
              "value": "10"
            }
          }
        }
      ]
    },
    "E2": {
      "descriptionTemplate": "{Elegance of Rose} DMG +25%, and each instance of DMG dealt temporarily increases Crit. Rate by 5%.",
      "descriptionArgs": {},
      "id": "enlighten.sorel.vintage-nectar",
      "ownerAwakenerId": 46,
      "slot": "E2",
      "displayName": "Vintage Nectar",
      "upgradeTargetIds": ["skill.sorel.elegance-of-rose"],
      "upgradePatches": [
        {
          "targetId": "skill.sorel.elegance-of-rose",
          "targetType": "skill",
          "operation": "replace_description",
          "descriptionTemplate": "Randomly deal [Damage:Arg1] DMG [Arg3] times. For each instance of DMG dealt, Temporarily Crit. Rate +5%. Restore [Heal:Arg2] HP at turn end.",
          "descriptionArgs": {}
        }
      ]
    },
    "E3": {
      "descriptionTemplate": "At the start of battle, {Embryo Fusion} +25%. Each time {Death Resistance} is triggered, {Embryo Fusion} +25%. For each instance of DMG Sorel deals this turn, her DMG dealt this turn increases by 3% of her ATK.",
      "descriptionArgs": {},
      "id": "enlighten.sorel.lustrous-pearl",
      "ownerAwakenerId": 46,
      "slot": "E3",
      "displayName": "Lustrous Pearl",
      "upgradeTargetIds": [],
      "upgradePatches": []
    }
  },
  "derivedSkills": []
}
